fenwick/__init__.py
fenwick/fenwick.py
fenwick/version.txt
fenwick-0.2.0.dist-info/LICENSE
fenwick-0.2.0.dist-info/METADATA
fenwick-0.2.0.dist-info/WHEEL
fenwick-0.2.0.dist-info/top_level.txt
fenwick-0.2.0.dist-info/RECORD
